pancakeswap_universal_router_decoder/__init__.py
pancakeswap_universal_router_decoder/_abi_builder.py
pancakeswap_universal_router_decoder/_constants.py
pancakeswap_universal_router_decoder/_decoder.py
pancakeswap_universal_router_decoder/_encoder.py
pancakeswap_universal_router_decoder/_enums.py
pancakeswap_universal_router_decoder/router_codec.py
pancakeswap_universal_router_decoder/utils.py
pancakeswap_universal_router_decoder-0.1.2.dist-info/licenses/LICENSE
pancakeswap_universal_router_decoder-0.1.2.dist-info/METADATA
pancakeswap_universal_router_decoder-0.1.2.dist-info/WHEEL
pancakeswap_universal_router_decoder-0.1.2.dist-info/top_level.txt
pancakeswap_universal_router_decoder-0.1.2.dist-info/RECORD
