Metadata-Version: 2.4
Name: pancakeswap-universal-router-decoder
Version: 0.1.2
Summary: Decode & Encode transactions sent to the Pancakeswap Universal Router. Support Pancakeswap V4
Author-email: kafeikui <kkffkk3@protonmail.com>
License: MIT License
Project-URL: Homepage, https://github.com/kafeikui/pancakeswap-universal-router-decoder
Keywords: blockchain,pancakeswap,pancakeswap V4,exchange,dex,universal router,swap,decoder,encoder,codec,wrapper,SDK
Classifier: Development Status :: 5 - Production/Stable
Classifier: Intended Audience :: Developers
Classifier: License :: OSI Approved :: MIT License
Classifier: Natural Language :: English
Classifier: Programming Language :: Python :: 3
Classifier: Programming Language :: Python :: 3.9
Classifier: Programming Language :: Python :: 3.10
Classifier: Programming Language :: Python :: 3.11
Classifier: Programming Language :: Python :: 3.12
Classifier: Programming Language :: Python :: 3.13
Classifier: Operating System :: OS Independent
Requires-Python: >=3.9
License-File: LICENSE
Requires-Dist: web3<8.0.0,>=6.0.0
Dynamic: license-file
